pyscut/__init__.py
pyscut/main.py
pyscut-0.4.dist-info/METADATA
pyscut-0.4.dist-info/WHEEL
pyscut-0.4.dist-info/entry_points.txt
pyscut-0.4.dist-info/top_level.txt
pyscut-0.4.dist-info/RECORD
