Metadata-Version: 2.4
Name: pyscut
Version: 0.4
Requires-Dist: pywin32
Dynamic: requires-dist
